googlesearch_py.py
googlesearch.py-1.6.1.dist-info/METADATA
googlesearch.py-1.6.1.dist-info/WHEEL
googlesearch.py-1.6.1.dist-info/top_level.txt
googlesearch.py-1.6.1.dist-info/RECORD
