Metadata-Version: 2.1
Name: googlesearch.py
Version: 1.6.1
Summary: The Google search scraper for the Python programming language.
Home-page: https://github.com/cj-praveen/googlesearch.py
Author: CJ Praveen
Keywords: googlesearch.py,python google search,google search pypi,google api
Requires-Dist: httpx
